fflocker/__init__.py
fflocker/file_locker.py
fflocker/folder_locker.py
fflocker-1.3.dist-info/METADATA
fflocker-1.3.dist-info/WHEEL
fflocker-1.3.dist-info/licenses/LICENSE
fflocker-1.3.dist-info/RECORD
