Metadata-Version: 2.1
Name: fflocker
Version: 1.3
Summary: Locking files/folders [FF] in GNU/Linux via text-based user interface (TUI).
Project-URL: Homepage, https://github.com/camarman/FFLocker
Project-URL: Bug Tracker, https://github.com/camarman/FFLocker/issues
Author: Arman Çam
License-File: LICENSE
Classifier: Development Status :: 5 - Production/Stable
Classifier: License :: OSI Approved :: MIT License
Classifier: Operating System :: POSIX :: Linux
Classifier: Programming Language :: Python :: 3
Requires-Python: >=3.7
